deap/__init__.py
deap/crawler.py
deap/file_clean.py
deap/file_reader.py
test/__init__.py
test/test_crawler.py
test/test_file_clean.py
test/test_file_handler.py
project_deap-0.0.3.dist-info/LICENSE.txt
project_deap-0.0.3.dist-info/METADATA
project_deap-0.0.3.dist-info/WHEEL
project_deap-0.0.3.dist-info/top_level.txt
project_deap-0.0.3.dist-info/RECORD
