Metadata-Version: 2.1
Name: project-deap
Version: 0.0.3
Summary: Data Engineering Analytics Platform
Home-page: https://github.com/JoseRoberts87/project-deap
Author: joseroberts87
Author-email: jose.roberts@intracitygeeks.org
License: UNKNOWN
Platform: UNKNOWN
Classifier: Programming Language :: Python :: 3
Classifier: License :: OSI Approved :: MIT License
Classifier: Operating System :: OS Independent
Requires-Python: >=3.6
